quantcoin/__init__.py
quantcoin/symbols/__init__.py
quantcoin/symbols/symbols.py
quantcoin-0.0.2.dist-info/METADATA
quantcoin-0.0.2.dist-info/WHEEL
quantcoin-0.0.2.dist-info/top_level.txt
quantcoin-0.0.2.dist-info/RECORD
