Metadata-Version: 2.1
Name: quantcoin
Version: 0.0.2
Summary: Package for backtesting and paper trading cryptocurrency.
Home-page: https://github.com/GetQuantCoin/quantcoin
Author: GetQuantCoin
Author-email: tuan@quantcoin.co
License: UNKNOWN
Platform: UNKNOWN
Requires-Dist: pandas
